noveum_trace/__init__.py
noveum_trace/agents.py
noveum_trace/context_managers.py
noveum_trace/py.typed
noveum_trace/streaming.py
noveum_trace/threads.py
noveum_trace/core/__init__.py
noveum_trace/core/client.py
noveum_trace/core/config.py
noveum_trace/core/context.py
noveum_trace/core/span.py
noveum_trace/core/trace.py
noveum_trace/decorators/__init__.py
noveum_trace/decorators/agent.py
noveum_trace/decorators/base.py
noveum_trace/decorators/llm.py
noveum_trace/decorators/retrieval.py
noveum_trace/decorators/tool.py
noveum_trace/integrations/__init__.py
noveum_trace/integrations/langchain/__init__.py
noveum_trace/integrations/langchain/langchain.py
noveum_trace/integrations/langchain/langchain_utils.py
noveum_trace/integrations/livekit/__init__.py
noveum_trace/integrations/livekit/livekit_constants.py
noveum_trace/integrations/livekit/livekit_session.py
noveum_trace/integrations/livekit/livekit_stt.py
noveum_trace/integrations/livekit/livekit_tts.py
noveum_trace/integrations/livekit/livekit_utils.py
noveum_trace/transport/__init__.py
noveum_trace/transport/batch_processor.py
noveum_trace/transport/http_transport.py
noveum_trace/utils/__init__.py
noveum_trace/utils/exceptions.py
noveum_trace/utils/llm_utils.py
noveum_trace/utils/logging.py
noveum_trace/utils/pii_redaction.py
noveum_trace/utils/serialization.py
noveum_trace/utils/tokenizers.py
noveum_trace-1.3.1.dist-info/METADATA
noveum_trace-1.3.1.dist-info/WHEEL
noveum_trace-1.3.1.dist-info/licenses/LICENSE
noveum_trace-1.3.1.dist-info/RECORD
