Metadata-Version: 2.4
Name: noveum-trace
Version: 1.3.1
Summary: Cloud-first, decorator-based tracing SDK for LLM applications and multi-agent systems
Project-URL: Homepage, https://github.com/Noveum/noveum-trace
Project-URL: Documentation, https://noveum-trace.readthedocs.io
Project-URL: Repository, https://github.com/Noveum/noveum-trace
Project-URL: Bug Tracker, https://github.com/Noveum/noveum-trace/issues
Project-URL: Changelog, https://github.com/Noveum/noveum-trace/blob/main/CHANGELOG.md
Author-email: Noveum Team <engineering@noveum.ai>
Maintainer-email: Noveum Team <engineering@noveum.ai>
License:                                  Apache License
License-File: LICENSE
Keywords: ai,anthropic,langchain,llm,monitoring,multi-agent,observability,openai,tracing
Classifier: Development Status :: 3 - Alpha
Classifier: Intended Audience :: Developers
Classifier: License :: OSI Approved :: Apache Software License
Classifier: Operating System :: OS Independent
Classifier: Programming Language :: Python :: 3
Classifier: Programming Language :: Python :: 3.9
Classifier: Programming Language :: Python :: 3.10
Classifier: Programming Language :: Python :: 3.11
Classifier: Programming Language :: Python :: 3.12
Classifier: Topic :: Scientific/Engineering :: Artificial Intelligence
Classifier: Topic :: Software Development :: Libraries :: Python Modules
Classifier: Topic :: System :: Monitoring
Requires-Python: >=3.9
Requires-Dist: python-dotenv>=0.19.0
Requires-Dist: pyyaml>=6.0.0
Requires-Dist: requests>=2.25.0
Requires-Dist: typing-extensions>=4.0.0; python_version < '3.10'
Provides-Extra: anthropic
Requires-Dist: anthropic>=0.3.0; extra == 'anthropic'
Provides-Extra: dev
Requires-Dist: anthropic>=0.3.0; extra == 'dev'
Requires-Dist: bandit>=1.7.0; extra == 'dev'
Requires-Dist: black>=23.0.0; extra == 'dev'
Requires-Dist: commitizen>=3.0.0; extra == 'dev'
Requires-Dist: isort>=5.12.0; extra == 'dev'
Requires-Dist: langchain-core>=0.1.0; extra == 'dev'
Requires-Dist: mypy>=1.0.0; extra == 'dev'
Requires-Dist: openai>=1.0.0; extra == 'dev'
Requires-Dist: pre-commit>=3.0.0; extra == 'dev'
Requires-Dist: pytest-asyncio>=0.21.0; extra == 'dev'
Requires-Dist: pytest-cov>=4.0.0; extra == 'dev'
Requires-Dist: pytest-mock>=3.10.0; extra == 'dev'
Requires-Dist: pytest-xdist>=3.0.0; extra == 'dev'
Requires-Dist: pytest>=7.0.0; extra == 'dev'
Requires-Dist: ruff>=0.1.0; extra == 'dev'
Requires-Dist: safety>=2.3.0; extra == 'dev'
Requires-Dist: tox>=4.0.0; extra == 'dev'
Requires-Dist: types-pyyaml>=6.0.0; extra == 'dev'
Requires-Dist: types-requests>=2.25.0; extra == 'dev'
Provides-Extra: langchain
Requires-Dist: langchain-core>=0.1.0; extra == 'langchain'
Provides-Extra: lint
Requires-Dist: bandit>=1.7.0; extra == 'lint'
Requires-Dist: black>=23.0.0; extra == 'lint'
Requires-Dist: isort>=5.12.0; extra == 'lint'
Requires-Dist: mypy>=1.0.0; extra == 'lint'
Requires-Dist: ruff>=0.1.0; extra == 'lint'
Requires-Dist: safety>=2.3.0; extra == 'lint'
Provides-Extra: livekit
Requires-Dist: livekit-agents>=1.0.0; extra == 'livekit'
Requires-Dist: livekit<2,>=1.0.19; extra == 'livekit'
Provides-Extra: openai
Requires-Dist: openai>=1.0.0; extra == 'openai'
Provides-Extra: test
Requires-Dist: pytest-asyncio>=0.21.0; extra == 'test'
Requires-Dist: pytest-cov>=4.0.0; extra == 'test'
Requires-Dist: pytest-mock>=3.10.0; extra == 'test'
Requires-Dist: pytest>=7.0.0; extra == 'test'
